{
    "index": {
        "speakers": [
            {
                "active": true,
                "slug": "adrian",
                "image": "adrian.jpg",
                "name": "Adrian Holovaty",
                "bio": "Adrian is co-creator and former co-BDFL of Django. He was working as lead developer at World Online when the team decided to open-source their homegrown collection of web development tools. These days he's making <a href='http://soundslice.com/'>Soundslice</a>.",
                "social": [
                    {"icon": "globe", "link": "http://www.holovaty.com/", "title": "website"},
                    {"icon": "twitter", "link": "https://twitter.com/adrianholovaty", "title": "twitter"},
                    {"icon": "youtube", "link": "https://www.youtube.com/adrianholovaty", "title": "youtube"}
                ]
            },
            {
                "active": true,
                "slug": "ola",
                "image": "ola.jpg",
                "name": "Ola Sitarska",
                "bio": "Ola Sitarska is a Django Developer at <a href='https://p.ota.to/'>Potato</a>. She started working with Django 6 years ago, when she discovered the power of Django admin and quickly fell in love with the beauty of Python. Last year, Ola started <a href='https://djangogirls.org/'>Django Girls</a>, an initiative to inspire more women to become programmers. Together with Ola Sendecka, she also co-authored the <a href='https://tutorial.djangogirls.org/'>Django Girls Tutorial</a>, which has been visited by more than 30.000 people so far. She is also a member of the Django Core Team, and part of the team responsible for the shipping of <a href='https://djangoproject.com/'>djangoproject.com</a> redesign. In 2015, she became a <a href='https://djangoproject.com/foundation/'>Django Software Foundation</a> board member. Ola is also known as A Person With The <a href='https://2013.djangocon.eu/'>Django Circus</a> Idea™. Her superpower is unstoppable enthusiasm.",
                "social": [
                    {"icon": "twitter", "link": "http://twitter.com/olasitarska", "title": "twitter"}
                ],
                "talks": [
                    {
                        "slug": "🐍🐴🎈",
                        "title": "Snakes, ponies and balloons: stories of teaching Django to thousands of women."
                    }
                ]
            },
            {
                "active": true,
                "slug": "alex",
                "image": "alex.jpg",
                "name": "Alex Gaynor",
                "bio": "I'm an emeritus Django core developer and former DSF director. I'm a software engineer for the United States Department of Veterans Affairs, and a director of the Python Software Foundation. I live in Washington D.C.",
                "social": [
                    {"icon": "globe", "link": "https://alexgaynor.net/", "title": "website"},
                    {"icon": "github", "link": "https://github.com/alex", "title": "github"}
                ],
                "talks": [
                    {
                        "slug": "7yrs-w-django",
                        "title": "7 years with Django, to core developer and back"
                    }
                ]
            },
            {
                "active": true,
                "slug": "lacey",
                "image": "lacey.jpg",
                "name": "Lacey Williams Henschel",
                "bio": "Lacey is a senior software developer for the University of Texas at Austin, but she telecommutes from Portland, OR. She's the co-organizer of <a href='http://djangogirls.org/portland/'>Django Girls Portland</a> and <a href='http://djangogirls.org/djangoconus/'>Django Girls Austin (happening at DjangoCon)</a>, and the Diversity Chair and Financial Aid Chair for <a href='https://2015.djangocon.us/'>DjangoCon US</a>. She recently wrote an article for Model View Culture on making tech events more accessible to people with disabilities. In her spare time, she's a Big Sister with Big Brothers Big Sisters, serves on the technical board of <a href='http://projectcallisto.org/'>Project Callisto</a>, and tries desperately to develop a green thumb.",
                "social": [
                    {"icon": "twitter", "link": "https://twitter.com/laceynwilliams", "title": "twitter"}
                ]
            },
            {
                "active": true,
                "slug": "andrew",
                "image": "andrew.jpg",
                "name": "Andrew Godwin",
                "bio": "Django core developer, backend engineer, occasional game developer, cheese appreciator, archer and pilot. The chances of finding him at a Django event are relatively high.",
                "social": [
                    {"icon": "globe", "link": "http://www.aeracode.org/", "title": "website"},
                    {"icon": "twitter", "link": "https://twitter.com/andrewgodwin", "title": "twitter"}
                ],
                "talks": [
                    {
                        "slug": "django-conspirancy",
                        "title": "Django: The Conspiracy"
                    }
                ]
            },
            {
                "active": false,
                "slug": "marc",
                "image": "marc.jpg",
                "name": "Marc Tamlyn",
                "bio": "Marc is a part of the Django core team. He's partially responsible for contrib.postgres, the Django: Under the Hood conference, <a href='http://ccbv.co.uk/'>ccbv.co.uk</a> and bringing small children to Django conferences in Europe. He's the lead developer at <a href='https://www.photocrowd.com/'>photocrowd.com</a>, based in Oxford, UK.",
                "social": [
                    {"icon": "twitter", "link": "https://twitter.com/mjtamlyn", "title": "twitter"}
                ]
            },
            {
                "active": false,
                "slug": "eric",
                "image": "eric.jpg",
                "name": "Eric Holscher",
                "bio": "Eric Holscher is a founder of both <a href='https://readthedocs.org/'>Read the Docs</a>, and <a href='http://conf.writethedocs.org/'>Write the Docs</a>. When he isn't helping improve the documentation world, he's out in the woods somewhere.",
                "social": [
                    {"icon": "globe", "link": "http://ericholscher.com/", "title": "website"},
                    {"icon": "twitter", "link": "https://twitter.com/ericholscher", "title": "twitter"}
                ]
            }
        ]
    }
}
